[{"date": "2026-03-10", "open": 9.3, "high": 9.5, "low": 9.0, "close": 9.1, "volume": 2080767}, {"date": "2026-03-11", "open": 9.1, "high": 9.18, "low": 9.0, "close": 9.16, "volume": 4750823}, {"date": "2026-03-12", "open": 9.12, "high": 9.2, "low": 9.0, "close": 9.1, "volume": 961795}, {"date": "2026-03-13", "open": 9.1, "high": 9.14, "low": 9.0, "close": 9.04, "volume": 1361178}, {"date": "2026-03-16", "open": 9.04, "high": 9.2, "low": 9.04, "close": 9.12, "volume": 1698923}, {"date": "2026-03-17", "open": 9.12, "high": 9.16, "low": 9.0, "close": 9.08, "volume": 612772}, {"date": "2026-03-18", "open": 9.2, "high": 9.2, "low": 9.0, "close": 9.04, "volume": 1503899}, {"date": "2026-03-19", "open": 9.2, "high": 9.2, "low": 9.0, "close": 9.02, "volume": 1224365}, {"date": "2026-03-23", "open": 9.0, "high": 9.2, "low": 9.0, "close": 9.0, "volume": 4626831}, {"date": "2026-03-24", "open": 9.0, "high": 9.06, "low": 9.0, "close": 9.02, "volume": 3957567}, {"date": "2026-03-25", "open": 9.02, "high": 9.08, "low": 9.0, "close": 9.0, "volume": 1930380}, {"date": "2026-03-26", "open": 9.0, "high": 9.1, "low": 9.0, "close": 9.0, "volume": 2740399}, {"date": "2026-03-27", "open": 9.0, "high": 9.1, "low": 9.0, "close": 9.0, "volume": 2214554}, {"date": "2026-03-30", "open": 9.02, "high": 9.2, "low": 9.0, "close": 9.0, "volume": 1476988}, {"date": "2026-03-31", "open": 9.0, "high": 9.12, "low": 9.0, "close": 9.12, "volume": 2158366}, {"date": "2026-04-01", "open": 9.2, "high": 9.48, "low": 9.08, "close": 9.1, "volume": 1422498}, {"date": "2026-04-02", "open": 9.2, "high": 9.3, "low": 9.08, "close": 9.08, "volume": 1463713}, {"date": "2026-04-07", "open": 9.06, "high": 9.22, "low": 9.04, "close": 9.2, "volume": 630949}, {"date": "2026-04-08", "open": 9.2, "high": 9.22, "low": 9.06, "close": 9.2, "volume": 1011345}, {"date": "2026-04-09", "open": 9.2, "high": 9.46, "low": 9.06, "close": 9.3, "volume": 2374806}, {"date": "2026-04-10", "open": 9.3, "high": 9.5, "low": 9.24, "close": 9.4, "volume": 1074982}, {"date": "2026-04-13", "open": 9.28, "high": 9.56, "low": 9.28, "close": 9.3, "volume": 2134174}, {"date": "2026-04-14", "open": 9.4, "high": 9.5, "low": 9.1, "close": 9.5, "volume": 932681}, {"date": "2026-04-15", "open": 9.56, "high": 9.56, "low": 9.1, "close": 9.56, "volume": 1365235}, {"date": "2026-04-16", "open": 9.36, "high": 9.7, "low": 9.14, "close": 9.7, "volume": 876682}, {"date": "2026-04-17", "open": 9.5, "high": 9.94, "low": 9.4, "close": 9.8, "volume": 223073388}, {"date": "2026-04-20", "open": 9.8, "high": 9.9, "low": 9.2, "close": 9.5, "volume": 338318}, {"date": "2026-04-21", "open": 9.46, "high": 9.8, "low": 9.3, "close": 9.5, "volume": 210958}, {"date": "2026-04-22", "open": 9.2, "high": 9.4, "low": 9.2, "close": 9.2, "volume": 212171}, {"date": "2026-04-23", "open": 9.2, "high": 9.26, "low": 9.2, "close": 9.24, "volume": 229860}, {"date": "2026-04-24", "open": 9.24, "high": 9.4, "low": 9.2, "close": 9.28, "volume": 183788}, {"date": "2026-04-27", "open": 9.28, "high": 9.3, "low": 9.02, "close": 9.2, "volume": 318604}, {"date": "2026-04-28", "open": 9.2, "high": 9.4, "low": 9.04, "close": 9.16, "volume": 546290}, {"date": "2026-04-29", "open": 9.2, "high": 9.4, "low": 9.1, "close": 9.3, "volume": 235140}, {"date": "2026-04-30", "open": 9.3, "high": 9.4, "low": 9.2, "close": 9.36, "volume": 160067}, {"date": "2026-05-04", "open": 9.24, "high": 9.36, "low": 9.1, "close": 9.1, "volume": 253765}, {"date": "2026-05-05", "open": 9.1, "high": 9.24, "low": 9.04, "close": 9.16, "volume": 230081}, {"date": "2026-05-06", "open": 9.1, "high": 9.36, "low": 9.1, "close": 9.1, "volume": 298711}, {"date": "2026-05-07", "open": 9.1, "high": 9.16, "low": 9.1, "close": 9.12, "volume": 132712}, {"date": "2026-05-08", "open": 9.12, "high": 9.14, "low": 9.1, "close": 9.1, "volume": 158086}]